nonebot_plugin_manager/__init__.py
nonebot_plugin_manager/_pip.py
nonebot_plugin_manager/handle.py
nonebot_plugin_manager/manager.py
nonebot_plugin_manager/parser.py
nonebot_plugin_manager/plugin.py
nonebot_plugin_manager-0.5.16.dist-info/WHEEL
nonebot_plugin_manager-0.5.16.dist-info/METADATA
nonebot_plugin_manager-0.5.16.dist-info/licenses/LICENSE
nonebot_plugin_manager-0.5.16.dist-info/RECORD
