Metadata-Version: 2.1
Name: nonebot_plugin_manager
Version: 0.5.16
Summary: Nonebot Plugin Manager base on import hook
License: MIT
Author-email: Jigsaw <j1g5aw@foxmail.com>
Requires-Python: >=3.8,<4.0
Requires-Dist: httpx<1.0.0,>=0.23.1
Requires-Dist: nonebot-adapter-onebot<3.0.0.0,>=2.2.2
Requires-Dist: nonebot2<3.0.0.0,>=2.0.0
Requires-Dist: pyyaml>=6.0
Project-URL: homepage, https://github.com/Jigsaw111/nonebot_plugin_manager
Project-URL: repository, https://github.com/Jigsaw111/nonebot_plugin_manager
